tkns/__init__.py
tkinter_n_s-1.0.0.dist-info/LICENSE.txt
tkinter_n_s-1.0.0.dist-info/METADATA
tkinter_n_s-1.0.0.dist-info/WHEEL
tkinter_n_s-1.0.0.dist-info/top_level.txt
tkinter_n_s-1.0.0.dist-info/RECORD
