Metadata-Version: 2.1
Name: tkinter-n_s
Version: 1.0.0
Summary: TK组件的非线性滑动
Home-page: https://github.com/leletxh/TK-nonlinear-sliding
Author: Liu Zichang
Author-email: 1926341659@qq.com
Classifier: Programming Language :: Python :: 3
Classifier: License :: OSI Approved :: MIT License
Classifier: Operating System :: OS Independent
Requires-Python: >=3.8
License-File: LICENSE.txt
